{
  "link": {
    "shortcut icon": "{base}/htdocs/img/favicon/favicon.png"
  },
  "layout": "default",
  "layoutError": "error",
  "dev": {
    "css": {
      "default": {
        "bt": "{tema}/htdocs/css/bootstrap.css",
        "principal": "{tema}/htdocs/css/principal.css"
      }
    },
    "js": {
      "default": {
        "bt": "{tema}/htdocs/js/bootstrap.bundle.js",
        "principal": "{tema}/htdocs/js/principal.js"
      }
    }
  },
  "prod": {
    "css": {
      "default": "{tema}/htdocs/css/default.bundle.css"
    },
    "js": {
      "default": "{tema}/htdocs/js/default.bundle.js"
    }
  }
}